envmodel/__init__.py
envmodel/config_handler.py
envmodel/fields.py
envmodel/py.typed
envmodel/version.py
envmodel-0.2.0.dist-info/licenses/LICENSE
envmodel-0.2.0.dist-info/METADATA
envmodel-0.2.0.dist-info/WHEEL
envmodel-0.2.0.dist-info/top_level.txt
envmodel-0.2.0.dist-info/RECORD
