Metadata-Version: 2.4
Name: envmodel
Version: 0.2.0
Author-email: Allen Institute for Artificial Intelligence <contact@allenai.org>
License:                                  Apache License
Project-URL: Homepage, https://github.com/cccaballero/envmodel
Project-URL: Repository, https://github.com/cccaballero/envmodel
Project-URL: Changelog, https://github.com/cccaballero/envmodel/blob/main/CHANGELOG.md
Classifier: Intended Audience :: Science/Research
Classifier: Development Status :: 3 - Alpha
Classifier: License :: OSI Approved :: Apache Software License
Classifier: Programming Language :: Python :: 3
Classifier: Topic :: Scientific/Engineering :: Artificial Intelligence
Requires-Python: >=3.12
License-File: LICENSE
Provides-Extra: dev
Requires-Dist: ruff; extra == "dev"
Requires-Dist: mypy<2.0,>=1.0; extra == "dev"
Requires-Dist: isort<6.1,>=5.12; extra == "dev"
Requires-Dist: pytest; extra == "dev"
Requires-Dist: pytest-sphinx; extra == "dev"
Requires-Dist: pytest-cov; extra == "dev"
Requires-Dist: pytest-mock; extra == "dev"
Requires-Dist: twine>=1.11.0; extra == "dev"
Requires-Dist: build; extra == "dev"
Requires-Dist: setuptools; extra == "dev"
Requires-Dist: wheel; extra == "dev"
Requires-Dist: Sphinx<9.0,>=6.0; extra == "dev"
Requires-Dist: furo==2024.8.6; extra == "dev"
Requires-Dist: myst-parser>=1.0; extra == "dev"
Requires-Dist: sphinx-copybutton; extra == "dev"
Requires-Dist: sphinx-autobuild; extra == "dev"
Requires-Dist: sphinx-autodoc-typehints==3.1.0; extra == "dev"
Requires-Dist: packaging; extra == "dev"
Dynamic: license-file
